Lab 05 - building a simple processor/part 4/CPU1.v
module cpu_tb;

    reg CLK, RESET;
    wire [31:0] PC;
    reg [31:0] INSTRUCTION;
    
    /* 
    ------------------------
     SIMPLE INSTRUCTION MEM
    ------------------------
    */
    
    // TODO: Initialize an array of registers (8x1024) named 'instr_mem' to be used as instruction memory
    reg [7:0] instr_mem[0:1023];

    // TODO: Create combinational logic to support CPU instruction fetching, given the Program Counter(PC) value 
    //       (make sure you include the delay for instruction fetching here)

    always @(PC) begin
        #2
        INSTRUCTION = {instr_mem[PC+3], instr_mem[PC+2], instr_mem[PC+1], instr_mem[PC]};
    end
    
    initial
    begin
        // Initialize instruction memory with the set of instructions you need execute on CPU
        
        // METHOD 1: manually loading instructions to instr_mem
        // {instr_mem[10'd3], instr_mem[10'd2], instr_mem[10'd1], instr_mem[10'd0]} = 32'b00000000000001000000000000000101;
        // {instr_mem[10'd7], instr_mem[10'd6], instr_mem[10'd5], instr_mem[10'd4]} = 32'b00000000000000100000000000001001;
        // {instr_mem[10'd11], instr_mem[10'd10], instr_mem[10'd9], instr_mem[10'd8]} = 32'b00000010000001100000010000000010;
        
        // METHOD 2: loading instr_mem content from instr_mem.mem file
        $readmemb("instr_mem.mem", instr_mem);
    end
    
    /* 
    -----
     CPU
    -----
    */
    cpu mycpu(PC, INSTRUCTION, CLK, RESET);

    initial
    begin
    
        // generate files needed to plot the waveform using GTKWave
        $dumpfile("cpu_wavedata.vcd");
		$dumpvars(0, cpu_tb);
        
        CLK = 1'b0;
        RESET = 1'b0;
        
        // TODO: Reset the CPU (by giving a pulse to RESET signal) to start the program execution
        #2
        RESET = 1'b1;

        #4
        RESET= 1'b0;
        
        // finish simulation after some time
        #100
        $finish;
        
    end
    
    // clock signal generation
    always
        #4 CLK = ~CLK;
        

endmodule


module cpu(PC, INSTRUCTION, CLK, RESET);
    // declare the ports
    output reg [31:0] PC;
    input [31:0] INSTRUCTION;
    input CLK, RESET;

    // declare the registers and wires
    reg [2:0] SEL;
    wire [7:0] OUT1, OUT2, NEGATIVE, OUT3, OUT4;
    wire [7:0] RESULT;
    reg [2:0] DESTINATION, SOURCE1, SOURCE2;
    reg WRITE , isNEGATIVE, isIMMEDIATE, branch, isJUMP = 0;
    wire [31:0] NEXT, extended_out, offset, branched_pc, new_pc, pc_out;
    wire ZERO, and_out;



    //instantiate all modules
    pc_adder add(PC, NEXT);
    reg_file a0(RESULT, OUT1, OUT2, DESTINATION, SOURCE1, SOURCE2, WRITE, CLK, RESET);
    twosCompliment t1(OUT2, NEGATIVE); // convert positive value to negative value
    selectMUX8 m1(NEGATIVE, OUT2, OUT3, isNEGATIVE); //choose negative value for sub and positive value for add
    selectMUX8 m2(INSTRUCTION[7:0], OUT3, OUT4, isIMMEDIATE); //choose immediate value or register value 
    alu a2(OUT1, OUT4, RESULT, SEL, ZERO);
    AND_gate a(ZERO, branch, and_out);
    selectMUX32 m3(branched_pc, NEXT, pc_out, and_out);
    sign_extend se(INSTRUCTION[23 : 16], extended_out);
    shift_left2 sl2(extended_out, offset);
    branch_adder ba(NEXT, offset, branched_pc);
    selectMUX32 m4(branched_pc, pc_out, new_pc, isJUMP);

    always @(posedge CLK) 
    begin
        #1 PC = new_pc; // write next PC value to the PC at a positive clock edge

        if(RESET) PC = 32'd0; // write zero to PC when RESET is high and at a positive clock edge 
        
    end

    //check the opcode and decode
    always @(INSTRUCTION) begin
        // get input and ouput addresses to the register file
        DESTINATION = INSTRUCTION[18:16]; // INADDRESS
        SOURCE1 = INSTRUCTION[10:8];      // OUTADDRESS1
        SOURCE2 = INSTRUCTION[2:0];       // OUTADDRESS2

        #1
        case(INSTRUCTION[31:24]) 
            8'd0 : 
                begin
                    WRITE = 1;
                    isNEGATIVE = 1'b0;
                    isIMMEDIATE = 1'b1;
                    SEL = 3'b000; // FORWARD
                    branch = 0;

                end
            8'd1 : 
                begin
                    WRITE = 1;
                    isNEGATIVE = 1'b0;
                    isIMMEDIATE = 1'b0;
                    SEL = 3'b000; // MOV
                    branch = 0;

                end
            8'd2 : 
                begin
                    WRITE = 1;
                    isNEGATIVE = 1'b0;
                    isIMMEDIATE = 1'b0;
                    SEL = 3'b001; // ADD
                    branch = 0;
                    
                end
            8'd3 : 
                begin
                    WRITE = 1;
                    isNEGATIVE = 1'b1;
                    isIMMEDIATE = 1'b0;
                    SEL = 3'b001; // SUB
                    branch = 0;
                    
                end
            8'd4 : 
                begin
                    WRITE = 1;
                    isNEGATIVE = 1'b0;
                    isIMMEDIATE = 1'b0;
                    SEL = 3'b010; // AND
                    branch = 0;
                    
                end
            8'd5 : 
                begin
                    WRITE = 1;
                    isNEGATIVE = 1'b0;
                    isIMMEDIATE = 1'b0;
                    SEL = 3'b011; // OR
                    branch = 0;
                    
                end
            8'd6 :
                begin
                    isJUMP = 1;
                    WRITE = 1;
                    isNEGATIVE = 1'b0;
                    isIMMEDIATE = 1'b0;
                    SEL = 3'b100; // jump
                    branch = 1;

                end
            8'd7:
                begin
                    WRITE = 1;
                    isNEGATIVE = 1'b1;
                    isIMMEDIATE = 1'b0;
                    SEL = 3'b001; // beq 
                    branch = 1;
                end
            
        endcase
    
    end

    

endmodule


 //module for 2's compliment
module twosCompliment(DATA, OUT);
   //declare input and output
   input [7:0] DATA;
   output [7:0] OUT;

   assign #1 OUT = ~DATA + 1;
endmodule

// select mux for 8 bit inputs
module selectMUX8(IN1, IN2, OUT, SELECT);
    input [7:0] IN1, IN2;
    input SELECT;
    output reg [7:0] OUT;

    always@(*) begin
        case(SELECT)
            1'b1: OUT <= IN1;
            1'b0: OUT <= IN2;
            default: OUT <= 8'd0;
        endcase
    end
endmodule

// module to increament PC value by 4
module pc_adder(IN, OUT);
    input [31:0] IN; // input address/ current instruction
    output [31:0] OUT; // output address/ next instruction

    assign #1 OUT = IN + 32'd4;
  
endmodule

// module for and gate
module AND_gate(in1,in2,out);
    input in1, in2;
    output reg out = 0;

    always @(*)
    begin
        if(in1 & in2)
        begin
          out = 1;
        end
    end

endmodule

// new pc adder module for j and beq instructions
module branch_adder(pcNext, offset, out);
    input [31:0] pcNext, offset;
    output [31:0] out;

    assign #2 out = pcNext + offset;

endmodule

// module for sign extend from 8 bit to 32 bit
module sign_extend(in, out);
    input [7 : 0] in;
    output [31 : 0] out;

    assign out[7 : 0] = in[7 : 0];
    assign out[31 : 8] = {24{in[7]}}; 

endmodule

// module for shift a given input by 2
module shift_left2(in, out);
    input [31 : 0] in;
    output [31 : 0] out;

    assign out = in << 2;

endmodule

// select mux for 32 bit inputs
module selectMUX32(IN1, IN2, OUT, SELECT);
    input [31:0] IN1, IN2;
    input SELECT;
    output reg [31:0] OUT;

    always@(*) begin
        case(SELECT)
            1'b1: OUT <= IN1;
            1'b0: OUT <= IN2;
            default: OUT <= 8'd0;
        endcase
    end
endmodule


//reg_file module
module reg_file(IN, OUT1, OUT2, INADDRESS, OUT1ADDRESS, OUT2ADDRESS, WRITE, CLK, RESET);
    
    reg [7:0] Registers[0:7]; //8 bit wide element array with depth of 8

    //declaration of inputs and ouputs
    input [7:0] IN;
    input [2:0] OUT1ADDRESS, OUT2ADDRESS, INADDRESS;
    input CLK, RESET, WRITE;
    output [7:0] OUT1, OUT2;

    integer i;

    //read asynchronously and load values into OUT1 and OUT2 
    assign #2 OUT1 = Registers[OUT1ADDRESS];
    assign #2 OUT2 = Registers[OUT2ADDRESS];

    //always block only teriggerd in the positive edge of clock
    always@(posedge CLK)
    begin
        if(WRITE & !RESET) begin// if write port is set to high and reset is low then IN port is write into register named as INADDRESS
           #1 Registers[INADDRESS] <= IN;
           
        end
        if(RESET) begin // if reset is high, all values in registers are written as 0
            #1
            for(i = 0; i < 8; i = i + 1) begin // make for loop for access each element in an array
                 Registers[i] <= 8'd0;
            end
        end

    end
    /* initial begin
     #100 $display($time, "%d %d %d %d %d %d %d %d\n", Registers[0], Registers[1], Registers[2], Registers[3], Registers[4], Registers[5], Registers[6], Registers[7]);
     end */
endmodule



module alu(DATA1, DATA2, RESULT, SELECT, ZERO);

  //declaration for inputs and output ports
  input [7:0] DATA1;
  input [7:0] DATA2;
  input [2:0] SELECT;
  output reg [7:0] RESULT;
  output reg ZERO = 0;

  //declaration of wires that hold vlues of each operation
  wire [7:0]a, b, c, d;

  //instantiate modules
  FORWARD ins1(DATA2, a);
  ADD ins2(DATA1, DATA2, b);
  AND ins5(DATA1, DATA2, c);
  OR ins6(DATA1, DATA2, d);

    always @(b) 
    begin
      if(b == 0)
      begin
        ZERO = 1;
      end
    end
    always@(DATA1, DATA2, SELECT)
    begin
      case(SELECT)
      //doing corresponding operation for each select value 
      3'b000 : assign RESULT = a; // RESULT = DATA2
      3'b001 : assign RESULT = b; //RESULT = DATA1 + DATA2
      3'b010 : assign RESULT = c; //RESULT = DATA1 & DATA2
      3'b011 : assign RESULT = d; //RESULT = DATA1 | DATA2
      default: assign RESULT = 8'd0; //in default RESULT is 0
      endcase


    end
    
endmodule

//FORWARD module
module FORWARD(DATA, OUT);

  //declare input and output
  input [7:0] DATA;
  output [7:0] OUT;

  assign #1 OUT = DATA;
endmodule


//module for addition
 module ADD(DATA1, DATA2, OUT);
//declare inputs and output
   input [7:0] DATA1;
   input [7:0] DATA2;
   output [7:0] OUT;

  assign #2 OUT = DATA1 + DATA2;

 endmodule


//module for and operation
module AND(DATA1, DATA2, OUT);
//declare inputs and output
   input [7:0] DATA1;
   input [7:0] DATA2;
   output [7:0] OUT;

  assign #1 OUT = DATA1 & DATA2;

 endmodule

//module for or operation
module OR(DATA1, DATA2, OUT);
  //declare inputs and output
   input [7:0] DATA1;
   input [7:0] DATA2;
   output [7:0] OUT;

  assign #1 OUT = DATA1 | DATA2;

 endmodule

Lab 05 - building a simple processor/part 4/cpu_wavedata.vcd
$date
	Wed Feb 02 09:19:58 2022
$end
$version
	Icarus Verilog
$end
$timescale
	1s
$end
$scope module cpu_tb $end
$var wire 32 ! PC [31:0] $end
$var reg 1 " CLK $end
$var reg 32 # INSTRUCTION [31:0] $end
$var reg 1 $ RESET $end
$scope module mycpu $end
$var wire 1 % CLK $end
$var wire 32 & INSTRUCTION [31:0] $end
$var wire 8 ' NEGATIVE [7:0] $end
$var wire 32 ( NEXT [31:0] $end
$var wire 8 ) OUT1 [7:0] $end
$var wire 8 * OUT2 [7:0] $end
$var wire 8 + OUT3 [7:0] $end
$var wire 8 , OUT4 [7:0] $end
$var wire 1 - RESET $end
$var wire 8 . RESULT [7:0] $end
$var wire 1 / ZERO $end
$var wire 1 0 and_out $end
$var wire 32 1 branched_pc [31:0] $end
$var wire 32 2 extended_out [31:0] $end
$var wire 32 3 new_pc [31:0] $end
$var wire 32 4 offset [31:0] $end
$var wire 32 5 pc_out [31:0] $end
$var reg 3 6 DESTINATION [2:0] $end
$var reg 32 7 PC [31:0] $end
$var reg 3 8 SEL [2:0] $end
$var reg 3 9 SOURCE1 [2:0] $end
$var reg 3 : SOURCE2 [2:0] $end
$var reg 1 ; WRITE $end
$var reg 1 < branch $end
$var reg 1 = isIMMEDIATE $end
$var reg 1 > isJUMP $end
$var reg 1 ? isNEGATIVE $end
$scope module add $end
$var wire 32 @ IN [31:0] $end
$var wire 32 A OUT [31:0] $end
$upscope $end
$scope module a0 $end
$var wire 1 % CLK $end
$var wire 8 B IN [7:0] $end
$var wire 3 C INADDRESS [2:0] $end
$var wire 8 D OUT1 [7:0] $end
$var wire 3 E OUT1ADDRESS [2:0] $end
$var wire 8 F OUT2 [7:0] $end
$var wire 3 G OUT2ADDRESS [2:0] $end
$var wire 1 - RESET $end
$var wire 1 H WRITE $end
$var integer 32 I i [31:0] $end
$upscope $end
$scope module t1 $end
$var wire 8 J DATA [7:0] $end
$var wire 8 K OUT [7:0] $end
$upscope $end
$scope module m1 $end
$var wire 8 L IN1 [7:0] $end
$var wire 8 M IN2 [7:0] $end
$var wire 1 N SELECT $end
$var reg 8 O OUT [7:0] $end
$upscope $end
$scope module m2 $end
$var wire 8 P IN1 [7:0] $end
$var wire 8 Q IN2 [7:0] $end
$var wire 1 R SELECT $end
$var reg 8 S OUT [7:0] $end
$upscope $end
$scope module a2 $end
$var wire 8 T DATA1 [7:0] $end
$var wire 8 U DATA2 [7:0] $end
$var wire 3 V SELECT [2:0] $end
$var wire 8 W a [7:0] $end
$var wire 8 X b [7:0] $end
$var wire 8 Y c [7:0] $end
$var wire 8 Z d [7:0] $end
$var reg 8 [ RESULT [7:0] $end
$var reg 1 \ ZERO $end
$scope module ins1 $end
$var wire 8 ] DATA [7:0] $end
$var wire 8 ^ OUT [7:0] $end
$upscope $end
$scope module ins2 $end
$var wire 8 _ DATA1 [7:0] $end
$var wire 8 ` DATA2 [7:0] $end
$var wire 8 a OUT [7:0] $end
$upscope $end
$scope module ins5 $end
$var wire 8 b DATA1 [7:0] $end
$var wire 8 c DATA2 [7:0] $end
$var wire 8 d OUT [7:0] $end
$upscope $end
$scope module ins6 $end
$var wire 8 e DATA1 [7:0] $end
$var wire 8 f DATA2 [7:0] $end
$var wire 8 g OUT [7:0] $end
$upscope $end
$upscope $end
$scope module a $end
$var wire 1 / in1 $end
$var wire 1 h in2 $end
$var reg 1 i out $end
$upscope $end
$scope module m3 $end
$var wire 32 j IN1 [31:0] $end
$var wire 32 k IN2 [31:0] $end
$var wire 1 0 SELECT $end
$var reg 32 l OUT [31:0] $end
$upscope $end
$scope module se $end
$var wire 8 m in [7:0] $end
$var wire 32 n out [31:0] $end
$upscope $end
$scope module sl2 $end
$var wire 32 o in [31:0] $end
$var wire 32 p out [31:0] $end
$upscope $end
$scope module ba $end
$var wire 32 q offset [31:0] $end
$var wire 32 r out [31:0] $end
$var wire 32 s pcNext [31:0] $end
$upscope $end
$scope module m4 $end
$var wire 32 t IN1 [31:0] $end
$var wire 32 u IN2 [31:0] $end
$var wire 1 v SELECT $end
$var reg 32 w OUT [31:0] $end
$upscope $end
$upscope $end
$upscope $end
$enddefinitions $end
#0
$dumpvars
bx w
0v
bx u
bx t
bx s
bx r
bx00 q
bx00 p
bx o
bx n
bx m
bx l
bx k
bx j
0i
xh
bx g
b0 f
bx e
bx d
b0 c
bx b
bx a
b0 `
bx _
bx ^
b0 ]
0\
b0 [
bx Z
bx Y
bx X
bx W
bx V
b0 U
bx T
b0 S
xR
b0 Q
bx P
b0 O
xN
bx M
bx L
bx K
bx J
bx I
xH
bx G
bx F
bx E
bx D
bx C
b0 B
bx A
bx @
x?
0>
x=
x<
x;
bx :
bx 9
bx 8
bx 7
bx 6
bx 5
bx00 4
bx 3
bx 2
bx 1
00
0/
b0 .
0-
b0 ,
b0 +
bx *
bx )
bx (
bx '
bx &
0%
0$
bx #
0"
bx !
$end
#1
b0 Y
b0 d
b0 W
b0 ^
#2
1$
1-
#4
1"
1%
#5
b1000 I
b0 7
b0 !
b0 @
#6
b100 w
b100 3
b100 l
b100 5
b100 u
b100 (
b100 A
b100 k
b100 s
0$
0-
#7
b10000 4
b10000 p
b10000 q
b101 :
b101 G
b0 9
b0 E
b100 6
b100 C
b101 P
b100 2
b100 n
b100 o
b100 m
b1000000000000000101 #
b1000000000000000101 &
#8
b101 S
b101 ,
b101 U
b101 ]
b101 `
b101 c
b101 f
bx O
bx +
bx Q
b0 [
0<
0h
b0 8
b0 V
1=
1R
0?
0N
1;
1H
0"
0%
#9
b0 O
b0 +
b0 Q
b0x0x Y
b0x0x d
bx1x1 Z
bx1x1 g
b101 W
b101 ^
b101 [
b101 .
b101 B
b10100 1
b10100 j
b10100 r
b10100 t
b0 *
b0 F
b0 J
b0 M
b0 )
b0 D
b0 T
b0 _
b0 b
b0 e
#10
b0 '
b0 K
b0 L
b0 Y
b0 d
b101 Z
b101 g
#11
b101 X
b101 a
#12
1"
1%
#13
b100 7
b100 !
b100 @
#14
b1000 w
b1000 3
b1000 l
b1000 5
b1000 u
b1000 (
b1000 A
b1000 k
b1000 s
#15
b101 [
b1001 S
b1001 ,
b1001 U
b1001 ]
b1001 `
b1001 c
b1001 f
b1000 4
b1000 p
b1000 q
b1 :
b1 G
b10 6
b10 C
b1001 P
b10 2
b10 n
b10 o
b10 m
b100000000000001001 #
b100000000000001001 &
#16
b1001 Z
b1001 g
b1001 W
b1001 ^
b1001 [
b1001 .
b1001 B
0"
0%
#17
b1001 X
b1001 a
b10000 1
b10000 j
b10000 r
b10000 t
#20
1"
1%
#21
b1000 7
b1000 !
b1000 @
#22
b1100 w
b1100 3
b1100 l
b1100 5
b1100 u
b1100 (
b1100 A
b1100 k
b1100 s
#23
b1001 [
b101 S
b101 ,
b101 U
b101 ]
b101 `
b101 c
b101 f
b10100 4
b10100 p
b10100 q
b101 :
b101 G
b101 6
b101 C
b101 P
b101 2
b101 n
b101 o
b101 m
b1010000000000000101 #
b1010000000000000101 &
#24
b101 Z
b101 g
b101 W
b101 ^
b101 [
b101 .
b101 B
0"
0%
#25
b101 X
b101 a
b100000 1
b100000 j
b100000 r
b100000 t
#28
1"
1%
#29
b1100 7
b1100 !
b1100 @
#30
b10000 w
b10000 3
b10000 l
b10000 5
b10000 u
b10000 (
b10000 A
b10000 k
b10000 s
#31
b101 O
b101 +
b101 Q
b10000 4
b10000 p
b10000 q
b100 9
b100 E
b100 6
b100 C
b100 2
b100 n
b100 o
b100 m
b101 *
b101 F
b101 J
b101 M
b111000001000000010000000101 #
b111000001000000010000000101 &
#32
b11111011 S
b11111011 ,
b11111011 U
b11111011 ]
b11111011 `
b11111011 c
b11111011 f
b11111011 O
b11111011 +
b11111011 Q
b101 [
b11111011 '
b11111011 K
b11111011 L
1<
1h
b1 8
b1 V
0=
0R
1?
1N
0"
0%
#33
b101 [
b11111011 Z
b11111011 g
b11111011 W
b11111011 ^
b101 )
b101 D
b101 T
b101 _
b101 b
b101 e
#34
b1 Y
b1 d
b11111111 Z
b11111111 g
#35
b100000 w
b100000 3
b100000 l
b100000 5
b100000 u
1i
10
1\
1/
b0 X
b0 a
b0 [
b0 .
b0 B
#36
1"
1%
#37
b100000 7
b100000 !
b100000 @
#38
b100100 (
b100100 A
b100100 k
b100100 s
#39
b1100 4
b1100 p
b1100 q
b0 [
b1 :
b1 G
b11 6
b11 C
b1 P
b11 2
b11 n
b11 o
b11 m
b0 )
b0 D
b0 T
b0 _
b0 b
b0 e
b11000000110000010000000001 #
b11000000110000010000000001 &
#40
b0 Y
b0 d
b11111011 Z
b11111011 g
0<
0h
0"
0%
#41
b110000 w
b110000 3
b110000 l
b110000 5
b110000 u
b110000 1
b110000 j
b110000 r
b110000 t
b0 *
b0 F
b0 J
b0 M
b11111011 X
b11111011 a
b11111011 [
b11111011 .
b11111011 B
#42
b11111011 [
b0 S
b0 ,
b0 U
b0 ]
b0 `
b0 c
b0 f
b0 O
b0 +
b0 Q
b0 '
b0 K
b0 L
#43
b0 Z
b0 g
b0 W
b0 ^
#44
b0 X
b0 a
b0 [
b0 .
b0 B
1"
1%
#45
b110000 7
b110000 !
b110000 @
#46
b110100 (
b110100 A
b110100 k
b110100 s
#47
bx00 4
bx00 p
bx00 q
bx :
bx G
bx 9
bx E
bx 6
bx C
bx P
bx 2
bx n
bx o
bx m
bx #
bx &
#48
0"
0%
#49
bx w
bx 3
bx l
bx 5
bx u
b0 [
bx 1
bx j
bx r
bx t
bx *
bx F
bx J
bx M
bx )
bx D
bx T
bx _
bx b
bx e
#50
b0 [
bx S
bx ,
bx U
bx ]
bx `
bx c
bx f
bx O
bx +
bx Q
bx '
bx K
bx L
bx Z
bx g
#51
bx Y
bx d
bx W
bx ^
bx X
bx a
bx [
bx .
bx B
#52
1"
1%
#53
bx 7
bx !
bx @
#54
bx (
bx A
bx k
bx s
